Generator/Mul/V0.2.1/sim/config_case4/rtl/Delay0000000002.v
 module Delay0000000002 (
    i_data, o_data
    , i_clk
 );
 // Input and output ports
 input [8-1:0] i_data;
 output [8-1:0] o_data;
 input i_clk;
 reg [8-1:0] data_d [0:1-1];
 always @(posedge i_clk) begin
     data_d[0] <= i_data;
 end
 assign o_data = data_d[1-1];
 endmodule

Generator/Mul/V0.2.1/sim/config_case4/rtl/Delay0000000001.v
 module Delay0000000001 (
    i_data, o_data
 );
 // Input and output ports
 input [8-1:0] i_data;
 output [8-1:0] o_data;
 assign o_data = i_data;
 endmodule

Generator/Mul/V0.2.1/sim/config_case3/rtl/FxMatch0000000001.v
 module FxMatch0000000001 (
     i_data, o_data
 );
 input wire [10-1:0] i_data;     // Input data
 output wire [9-1:0] o_data;   // Output data
 //
 wire [11-1:0] i_data_eq;
 assign i_data_eq = {1'b0, i_data};
 wire [10-1:0] o_data_eq;
 // Quantization Stage
 // Pad extra LSB bits with 0
 wire [12-1:0] op_quan; // Quantization output
 assign op_quan = {i_data_eq, {1{1'b0}}};
 // Overflow Stage
 // Overflow protection
 assign o_data_eq = op_quan[10-1:0];
 wire [9-1:0] o_data_trunc;
 // Truncate the sign bit for unsigned output
 assign o_data_trunc = o_data_eq[10-2:0];
Delay0000000001  u_0000000001_Delay0000000001(.i_data(o_data_trunc), .o_data(o_data));
 endmodule

Generator/BasicModules/Mul/sim/config_case1/rtl/Mul0000000001.v
 module Mul0000000001 (
 i_data_1, i_data_2, o_data
    ,i_clk
 );
 input wire [3:0] i_data_1;
 input wire [3:0] i_data_2;
 output wire [6:0] o_data;
 input wire i_clk;
 wire [3:0] data_1;
 wire [3:0] data_2;
 assign data_1 = i_data_1;
 assign data_2 = i_data_2;
 wire [3:0] data_1_abs;
 wire [3:0] data_2_abs;
 wire [7:0] data_mul_ures;
 assign data_1_abs = data_1[3] ? {~data_1[3:0] + 1'b1} : data_1;
 assign data_2_abs = data_2[3] ? {~data_2[3:0] + 1'b1} : data_2;
 assign data_mul_ures = data_1_abs * data_2_abs;
 wire res_sign;
 wire [8:0] data_mul_res;
 assign res_sign = data_1[3] ^ data_2[3];
 assign data_mul_res = res_sign ? {~{1'b0, data_mul_ures[7:0]} + 1'b1} : {1'b0, data_mul_ures};
 wire [6:0] result_fixed;
FxMatch0000000001  u_0000000001_FxMatch0000000001(.i_data(data_mul_res), .o_data(result_fixed));
Delay0000000002  u_0000000001_Delay0000000002(.i_data(result_fixed), .o_data(o_data), .i_clk(i_clk));
 endmodule

Generator/Mul/V0.2.1/sim/config_case1/workspace/RTL/TbMul0000000001.v
 `timescale 1ns/1ps
 module TbMul0000000001 ;
 // Inputs
 reg [4-1:0] Input_i_data_1;
 reg [4 -1:0] Input_i_data_2;
 reg [4-1:0] i_data_1;
 reg [4 -1:0] i_data_2;
 reg clk;
 reg en;
 reg i_rst_n;
 // Outputs
 wire [7-1:0] o_data;
 // Input ready and Output ready Indicators
 reg Input_rdy;
 reg Output_rdy;
 // Instantiate the DUT
 // Instantiate the DUT
Mul0000000001  u_0000000001_Mul0000000001(.i_data_1(i_data_1), .i_data_2(i_data_2), .o_data(o_data), .i_clk(clk));
 // Drive clk signal
 initial
 begin
     clk = 0;
      forever #2.5  clk <= ~clk;
 end
 // Initialize Inputs
 initial begin
 i_data_1 <= 'b0;
 i_data_2 <= 'b0;
 end
 // Enable signal
 initial begin
 en <= 0;
 repeat (3) @(posedge clk);
 en <= 1;
 end
 // Drive rst signal
 initial
 begin
     i_rst_n <= 1;
     repeat (1) @(negedge clk);
     i_rst_n <= 0;
     repeat (1) @(negedge clk);
     i_rst_n <= 1;
 end
 // Drive input ready and output ready signal
 integer Input_rdy_iter;
 initial begin
 Input_rdy <= 0;
 repeat (1) @(posedge en);
 Input_rdy <= 1;
 for (Input_rdy_iter=0; Input_rdy_iter<36; Input_rdy_iter=Input_rdy_iter+1) begin
     # (2.5) Input_rdy <= ~ Input_rdy;
 end
 end
 integer Output_rdy_iter;
 initial begin
 Output_rdy <= 0;
 repeat(1) @(posedge en);
 repeat (1) @(posedge clk); // wait for 1 cycles
 Output_rdy <= 1;
 for (Output_rdy_iter=0; Output_rdy_iter<36; Output_rdy_iter=Output_rdy_iter+1) begin
     # (2.5) Output_rdy <= ~ Output_rdy;
 end
 repeat(30) @(posedge clk);
 $finish;
 end
 // Drive input signal
 integer i_data_1_dat, i_data_1_st;
 initial begin
 repeat (2) @(posedge clk);
 i_data_1_dat = $fopen("../Input_Files/Mul_i_data_1.txt", "r");
 while (!$feof(i_data_1_dat)) begin
     i_data_1_st = $fscanf(i_data_1_dat, "%b\n", Input_i_data_1);
      repeat(1) @(posedge Input_rdy);
     i_data_1 <= Input_i_data_1;
 end
 $fclose(i_data_1_dat);
 end
 integer i_data_2_dat, i_data_2_st;
 initial begin
 repeat (2) @(posedge clk);
 i_data_2_dat = $fopen("../Input_Files/Mul_i_data_2.txt", "r");
 while (!$feof(i_data_2_dat)) begin
     i_data_2_st = $fscanf(i_data_2_dat, "%b\n", Input_i_data_2);
      repeat(1) @(posedge Input_rdy);
     i_data_2 <= Input_i_data_2;
 end
 $fclose(i_data_2_dat);
 end
 // Dump output signal
 integer o_data_dat;
 integer o_data_iter;
 initial begin
 repeat (2) @(posedge clk);
 o_data_dat = $fopen("../Output_Files/Mul_o_data.txt", "w");
 for (o_data_iter=0; o_data_iter<8; o_data_iter=o_data_iter+1) begin
     repeat(1) @(posedge Output_rdy);
     repeat(1) @(negedge clk);
     $fdisplay(o_data_dat, "%b", o_data);
 end
 $fclose(o_data_dat);
 end
 initial begin
     $dumpfile("wave.vcd");
     $dumpvars(0, TbMul0000000001);
 end
 endmodule

Generator/Mul/V0.2.1/sim/config_case1/workspace/RTL/wave.vcd
$date
	Fri Sep 11 10:48:44 2026
$end
$version
	Icarus Verilog
$end
$timescale
	1ps
$end
$scope module TbMul0000000001 $end
$var wire 7 ! o_data [6:0] $end
$var reg 4 " Input_i_data_1 [3:0] $end
$var reg 4 # Input_i_data_2 [3:0] $end
$var reg 1 $ Input_rdy $end
$var reg 1 % Output_rdy $end
$var reg 1 & clk $end
$var reg 1 ' en $end
$var reg 4 ( i_data_1 [3:0] $end
$var reg 4 ) i_data_2 [3:0] $end
$var reg 1 * i_rst_n $end
$var integer 32 + Input_rdy_iter [31:0] $end
$var integer 32 , Output_rdy_iter [31:0] $end
$var integer 32 - i_data_1_dat [31:0] $end
$var integer 32 . i_data_1_st [31:0] $end
$var integer 32 / i_data_2_dat [31:0] $end
$var integer 32 0 i_data_2_st [31:0] $end
$var integer 32 1 o_data_dat [31:0] $end
$var integer 32 2 o_data_iter [31:0] $end
$scope module u_0000000001_Mul0000000001 $end
$var wire 4 3 data_1 [3:0] $end
$var wire 4 4 data_2 [3:0] $end
$var wire 1 & i_clk $end
$var wire 4 5 i_data_1 [3:0] $end
$var wire 4 6 i_data_2 [3:0] $end
$var wire 1 7 res_sign $end
$var wire 7 8 result_fixed [6:0] $end
$var wire 7 9 o_data [6:0] $end
$var wire 8 : data_mul_ures [7:0] $end
$var wire 9 ; data_mul_res [8:0] $end
$var wire 4 < data_2_abs [3:0] $end
$var wire 4 = data_1_abs [3:0] $end
$scope module u_0000000001_Delay0000000002 $end
$var wire 1 & i_clk $end
$var wire 7 > o_data [6:0] $end
$var wire 7 ? i_data [6:0] $end
$upscope $end
$scope module u_0000000001_FxMatch0000000001 $end
$var wire 9 @ i_data [8:0] $end
$var wire 9 A i_data_eq [8:0] $end
$var wire 7 B o_data_trunc [6:0] $end
$var wire 8 C op_quan [7:0] $end
$var wire 7 D o_data_eq [6:0] $end
$var wire 7 E o_data [6:0] $end
$scope module u_0000000001_Delay0000000001 $end
$var wire 7 F i_data [6:0] $end
$var wire 7 G o_data [6:0] $end
$upscope $end
$upscope $end
$upscope $end
$upscope $end
$enddefinitions $end
$comment Show the parameter values. $end
$dumpall
$end
#0
$dumpvars
b0 G
b0 F
b0 E
b0 D
b0 C
b0 B
b0 A
b0 @
b0 ?
bx >
b0 =
b0 <
b0 ;
b0 :
bx 9
b0 8
07
b0 6
b0 5
b0 4
b0 3
bx 2
bx 1
bx 0
bx /
bx .
bx -
bx ,
bx +
1*
b0 )
b0 (
0'
0&
0%
0$
bx #
bx "
bx !
$end
#2500
b0 !
b0 9
b0 >
1&
#5000
0*
0&
#7500
b0 2
b10000000000000000000000000000101 1
b1 0
b111 #
b10000000000000000000000000000100 /
b1 .
b1110 "
b10000000000000000000000000000011 -
1&
#10000
1*
0&
#12500
b1111001 8
b1111001 ?
b1111001 E
b1111001 G
b1111001 B
b1111001 F
b1111001 D
b11111001 C
b111110010 A
b111110010 ;
b111110010 @
b1110 :
17
b10 =
b111 <
b1110 3
b1110 (
b1110 5
b111 4
b111 )
b111 6
b11 "
b110 #
1$
b0 +
1'
1&
#15000
0$
0&
b1 +
#17500
b1001 8
b1001 ?
b1001 E
b1001 G
b1001 B
b1001 F
b1001 D
b1001 C
b10010 A
b10010 ;
b10010 @
b10010 :
b11 =
07
b110 <
b110 4
b110 )
b110 6
b11 3
b11 (
b11 5
b1111001 !
b1111001 9
b1111001 >
1%
b1010 #
b1000 "
b0 ,
1$
1&
b10 +
#20000
b1 2
0%
0$
0&
b1 ,
b11 +
#22500
b11000 8
b11000 ?
b11000 E
b11000 G
b11000 B
b11000 F
b11000 D
b11000 C
b110000 A
b110000 ;
b110000 @
b110000 :
b1000 =
b110 <
b1000 3
b1000 (
b1000 5
b1010 4
b1010 )
b1010 6
b1001 !
b1001 9
b1001 >
b1100 "
b111 #
1%
1$
1&
b10 ,
b100 +
#25000
b10 2
0%
0$
0&
b11 ,
b101 +
#27500
b1110010 8
b1110010 ?
b1110010 E
b1110010 G
b1110010 B
b1110010 F
b1110010 D
b11110010 C
b111100100 A
b111100100 ;
b111100100 @
b11100 :
b111 <
17
b100 =
b111 4
b111 )
b111 6
b1100 3
b1100 (
b1100 5
b11000 !
b11000 9
b11000 >
b1011 #
b1010 "
1%
1$
1&
b100 ,
b110 +
#30000
b11 2
0%
0$
0&
b101 ,
b111 +
#32500
b1111 8
b1111 ?
b1111 E
b1111 G
b1111 B
b1111 F
b1111 D
b1111 C
b11110 A
b11110 ;
b11110 @
b110 =
b11110 :
07
b101 <
b1010 3
b1010 (
b1010 5
b1011 4
b1011 )
b1011 6
b1110010 !
b1110010 9
b1110010 >
b1001 "
b1110 #
1%
1$
1&
b110 ,
b1000 +
#35000
b100 2
0%
0$
0&
b111 ,
b1001 +
#37500
b111 8
b111 ?
b111 E
b111 G
b111 B
b111 F
b111 D
b111 C
b1110 A
b1110 ;
b1110 @
b1110 :
b10 <
b111 =
b1110 4
b1110 )
b1110 6
b1001 3
b1001 (
b1001 5
b1111 !
b1111 9
b1111 >
b1010 "
1%
1$
1&
b1000 ,
b1010 +
#40000
b101 2
0%
0$
0&
b1001 ,
b1011 +
#42500
b110 8
b110 ?
b110 E
b110 G
b110 B
b110 F
b110 D
b110 C
b1100 A
b1100 ;
b1100 @
b1100 :
b110 =
b1010 3
b1010 (
b1010 5
b111 !
b111 9
b111 >
b1101 "
b10 #
1%
1$
1&
b1010 ,
b1100 +
#45000
b110 2
0%
0$
0&
b1011 ,
b1101 +
#47500
b1111101 8
b1111101 ?
b1111101 E
b1111101 G
b1111101 B
b1111101 F
b1111101 D
b11111101 C
b111111010 A
b111111010 ;
b111111010 @
b110 :
17
b11 =
b10 4
b10 )
b10 6
b1101 3
b1101 (
b1101 5
b110 !
b110 9
b110 >
1%
1$
1&
b1100 ,
b1110 +
#50000
b111 2
0%
0$
0&
b1101 ,
b1111 +
#52500
b1111101 !
b1111101 9
b1111101 >
1%
1$
1&
b1110 ,
b10000 +
#55000
b1000 2
0%
0$
0&
b1111 ,
b10001 +
#57500
1%
1$
1&
b10000 ,
b10010 +
#60000
0%
0$
0&
b10001 ,
b10011 +
#62500
1%
1$
1&
b10010 ,
b10100 +
#65000
0%
0$
0&
b10011 ,
b10101 +
#67500
1%
1$
1&
b10100 ,
b10110 +
#70000
0%
0$
0&
b10101 ,
b10111 +
#72500
1%
1$
1&
b10110 ,
b11000 +
#75000
0%
0$
0&
b10111 ,
b11001 +
#77500
1%
1$
1&
b11000 ,
b11010 +
#80000
0%
0$
0&
b11001 ,
b11011 +
#82500
1%
1$
1&
b11010 ,
b11100 +
#85000
0%
0$
0&
b11011 ,
b11101 +
#87500
1%
1$
1&
b11100 ,
b11110 +
#90000
0%
0$
0&
b11101 ,
b11111 +
#92500
1%
1$
1&
b11110 ,
b100000 +
#95000
0%
0$
0&
b11111 ,
b100001 +
#97500
1%
1$
1&
b100000 ,
b100010 +
#100000
0%
0$
0&
b100001 ,
b100011 +
#102500
1%
1$
1&
b100010 ,
b100100 +
#105000
0%
0&
b100011 ,
#107500
1%
1&
b100100 ,
