Generator/BasicModules/Mul/sim/config_case1/workspace/RTL/Delay0000000002.v
 module Delay0000000002 (
    i_data, o_data
    , i_clk
 );
 // Input and output ports
 input [7-1:0] i_data;
 output [7-1:0] o_data;
 input i_clk;
 reg [7-1:0] data_d [0:1-1];
 always @(posedge i_clk) begin
     data_d[0] <= i_data;
 end
 assign o_data = data_d[1-1];
 endmodule

Generator/BasicModules/Mul/sim/config_case1/rtl/Delay0000000001.v
 module Delay0000000001 (
    i_data, o_data
 );
 // Input and output ports
 input [7-1:0] i_data;
 output [7-1:0] o_data;
 assign o_data = i_data;
 endmodule

Generator/BasicModules/Mul/sim/config_case5/rtl/FxMatch0000000001.v
 module FxMatch0000000001 (
     i_data, o_data
 );
 input wire [13-1:0] i_data;     // Input data
 output wire [9-1:0] o_data;   // Output data
 //
 wire [14-1:0] i_data_eq;
 assign i_data_eq = {1'b0, i_data};
 wire [10-1:0] o_data_eq;
 // Quantization Stage
 wire [13-1:0] op_quan; // Quantization output
 assign op_quan = i_data_eq[14-1:1];
 // Overflow Stage
 // Overflow protection
 assign o_data_eq = op_quan[10-1:0];
 wire [9-1:0] o_data_trunc;
 // Truncate the sign bit for unsigned output
 assign o_data_trunc = o_data_eq[10-2:0];
Delay0000000001  u_0000000001_Delay0000000001(.i_data(o_data_trunc), .o_data(o_data));
 endmodule

Generator/BasicModules/Mul/sim/config_case4/workspace/RTL/Mul0000000001.v
 module Mul0000000001 (
 i_data_1, i_data_2, o_data
    ,i_clk
 );
 input wire [4:0] i_data_1;
 input wire [5:0] i_data_2;
 output wire [7:0] o_data;
 input wire i_clk;
 wire [4:0] data_1;
 wire [5:0] data_2;
 assign data_1 = i_data_1;
 assign data_2 = i_data_2;
 wire [4:0] data_1_abs;
 wire [5:0] data_2_abs;
 wire [10:0] data_mul_ures;
 assign data_1_abs =  data_1;
 assign data_2_abs =  data_2;
 assign data_mul_ures = data_1_abs * data_2_abs;
 wire res_sign;
 wire [11:0] data_mul_res;
 assign res_sign = 1'b0;
 assign data_mul_res = {1'b0, data_mul_ures};
 wire [7:0] result_fixed;
FxMatch0000000001  u_0000000001_FxMatch0000000001(.i_data(data_mul_res), .o_data(result_fixed));
Delay0000000002  u_0000000001_Delay0000000002(.i_data(result_fixed), .o_data(o_data), .i_clk(i_clk));
 endmodule

Generator/BasicModules/Mul/sim/config_case4/workspace/RTL/TbMul0000000001.v
 `timescale 1ns/1ps
 module TbMul0000000001 ;
 // Inputs
 reg [5-1:0] Input_i_data_1;
 reg [6 -1:0] Input_i_data_2;
 reg [5-1:0] i_data_1;
 reg [6 -1:0] i_data_2;
 reg clk;
 reg en;
 reg i_rst_n;
 // Outputs
 wire [8-1:0] o_data;
 // Input ready and Output ready Indicators
 reg Input_rdy;
 reg Output_rdy;
 // Instantiate the DUT
 // Instantiate the DUT
Mul0000000001  u_0000000001_Mul0000000001(.i_data_1(i_data_1), .i_data_2(i_data_2), .o_data(o_data), .i_clk(clk));
 // Drive clk signal
 initial
 begin
     clk = 0;
      forever #5.0  clk <= ~clk;
 end
 // Initialize Inputs
 initial begin
 i_data_1 <= 'b0;
 i_data_2 <= 'b0;
 end
 // Enable signal
 initial begin
 en <= 0;
 repeat (3) @(posedge clk);
 en <= 1;
 end
 // Drive rst signal
 initial
 begin
     i_rst_n <= 1;
     repeat (1) @(negedge clk);
     i_rst_n <= 0;
     repeat (1) @(negedge clk);
     i_rst_n <= 1;
 end
 // Drive input ready and output ready signal
 integer Input_rdy_iter;
 initial begin
 Input_rdy <= 0;
 repeat (1) @(posedge en);
 Input_rdy <= 1;
 for (Input_rdy_iter=0; Input_rdy_iter<36; Input_rdy_iter=Input_rdy_iter+1) begin
     # (5.0) Input_rdy <= ~ Input_rdy;
 end
 end
 integer Output_rdy_iter;
 initial begin
 Output_rdy <= 0;
 repeat(1) @(posedge en);
 repeat (1) @(posedge clk); // wait for 1 cycles
 Output_rdy <= 1;
 for (Output_rdy_iter=0; Output_rdy_iter<36; Output_rdy_iter=Output_rdy_iter+1) begin
     # (5.0) Output_rdy <= ~ Output_rdy;
 end
 repeat(30) @(posedge clk);
 $finish;
 end
 // Drive input signal
 integer i_data_1_dat, i_data_1_st;
 initial begin
 repeat (2) @(posedge clk);
 i_data_1_dat = $fopen("../Input_Files/Mul_i_data_1.txt", "r");
 while (!$feof(i_data_1_dat)) begin
     i_data_1_st = $fscanf(i_data_1_dat, "%b\n", Input_i_data_1);
      repeat(1) @(posedge Input_rdy);
     i_data_1 <= Input_i_data_1;
 end
 $fclose(i_data_1_dat);
 end
 integer i_data_2_dat, i_data_2_st;
 initial begin
 repeat (2) @(posedge clk);
 i_data_2_dat = $fopen("../Input_Files/Mul_i_data_2.txt", "r");
 while (!$feof(i_data_2_dat)) begin
     i_data_2_st = $fscanf(i_data_2_dat, "%b\n", Input_i_data_2);
      repeat(1) @(posedge Input_rdy);
     i_data_2 <= Input_i_data_2;
 end
 $fclose(i_data_2_dat);
 end
 // Dump output signal
 integer o_data_dat;
 integer o_data_iter;
 initial begin
 repeat (2) @(posedge clk);
 o_data_dat = $fopen("../Output_Files/Mul_o_data.txt", "w");
 for (o_data_iter=0; o_data_iter<8; o_data_iter=o_data_iter+1) begin
     repeat(1) @(posedge Output_rdy);
     repeat(1) @(negedge clk);
     $fdisplay(o_data_dat, "%b", o_data);
 end
 $fclose(o_data_dat);
 end
 initial begin
     $dumpfile("wave.vcd");
     $dumpvars(0, TbMul0000000001);
 end
 endmodule

Generator/BasicModules/Mul/sim/config_case4/wave.vcd
$date
	Wed Sep 30 16:56:51 2026
$end
$version
	Icarus Verilog
$end
$timescale
	1ps
$end
$scope module TbMul0000000001 $end
$var wire 8 ! o_data [7:0] $end
$var reg 5 " Input_i_data_1 [4:0] $end
$var reg 6 # Input_i_data_2 [5:0] $end
$var reg 1 $ Input_rdy $end
$var reg 1 % Output_rdy $end
$var reg 1 & clk $end
$var reg 1 ' en $end
$var reg 5 ( i_data_1 [4:0] $end
$var reg 6 ) i_data_2 [5:0] $end
$var reg 1 * i_rst_n $end
$var integer 32 + Input_rdy_iter [31:0] $end
$var integer 32 , Output_rdy_iter [31:0] $end
$var integer 32 - i_data_1_dat [31:0] $end
$var integer 32 . i_data_1_st [31:0] $end
$var integer 32 / i_data_2_dat [31:0] $end
$var integer 32 0 i_data_2_st [31:0] $end
$var integer 32 1 o_data_dat [31:0] $end
$var integer 32 2 o_data_iter [31:0] $end
$scope module u_0000000001_Mul0000000001 $end
$var wire 5 3 data_1 [4:0] $end
$var wire 5 4 data_1_abs [4:0] $end
$var wire 6 5 data_2 [5:0] $end
$var wire 6 6 data_2_abs [5:0] $end
$var wire 1 & i_clk $end
$var wire 5 7 i_data_1 [4:0] $end
$var wire 6 8 i_data_2 [5:0] $end
$var wire 1 9 res_sign $end
$var wire 8 : result_fixed [7:0] $end
$var wire 8 ; o_data [7:0] $end
$var wire 11 < data_mul_ures [10:0] $end
$var wire 12 = data_mul_res [11:0] $end
$scope module u_0000000001_Delay0000000002 $end
$var wire 1 & i_clk $end
$var wire 8 > o_data [7:0] $end
$var wire 8 ? i_data [7:0] $end
$upscope $end
$scope module u_0000000001_FxMatch0000000001 $end
$var wire 12 @ i_data [11:0] $end
$var wire 13 A op_quan [12:0] $end
$var wire 8 B o_data_trunc [7:0] $end
$var wire 9 C o_data_eq [8:0] $end
$var wire 8 D o_data [7:0] $end
$var wire 13 E i_data_eq [12:0] $end
$scope module u_0000000001_Delay0000000001 $end
$var wire 8 F i_data [7:0] $end
$var wire 8 G o_data [7:0] $end
$upscope $end
$upscope $end
$upscope $end
$upscope $end
$enddefinitions $end
$comment Show the parameter values. $end
$dumpall
$end
#0
$dumpvars
b0 G
b0 F
b0 E
b0 D
b0 C
b0 B
b0 A
b0 @
b0 ?
bx >
b0 =
b0 <
bx ;
b0 :
09
b0 8
b0 7
b0 6
b0 5
b0 4
b0 3
bx 2
bx 1
bx 0
bx /
bx .
bx -
bx ,
bx +
1*
b0 )
b0 (
0'
0&
0%
0$
bx #
bx "
bx !
$end
#5000
b0 !
b0 ;
b0 >
1&
#10000
0*
0&
#15000
b0 2
b10000000000000000000000000000101 1
b1 0
b111111 #
b10000000000000000000000000000100 /
b1 .
b11010 "
b10000000000000000000000000000011 -
1&
#20000
1*
0&
#25000
b1100110 :
b1100110 ?
b1100110 D
b1100110 G
b1100110 B
b1100110 F
b1100110 C
b11001100110 A
b11001100110 E
b11001100110 =
b11001100110 @
b11001100110 <
b11010 4
b11010 3
b11010 (
b11010 7
b111111 6
b111111 5
b111111 )
b111111 8
b1110 "
b110111 #
1$
b0 +
1'
1&
#30000
0$
0&
b1 +
#35000
b10 :
b10 ?
b10 D
b10 G
b10 B
b10 F
b100000010 C
b1100000010 A
b1100000010 E
b1100000010 =
b1100000010 @
b1100000010 <
b110111 6
b110111 5
b110111 )
b110111 8
b1110 4
b1110 3
b1110 (
b1110 7
b1100110 !
b1100110 ;
b1100110 >
1%
b10000 #
b0 "
b0 ,
1$
1&
b10 +
#40000
b1 2
0%
0$
0&
b1 ,
b11 +
#45000
b0 :
b0 ?
b0 D
b0 G
b0 B
b0 F
b0 C
b0 A
b0 E
b0 =
b0 @
b0 <
b0 4
b0 3
b0 (
b0 7
b10000 6
b10000 5
b10000 )
b10000 8
b10 !
b10 ;
b10 >
b10011 "
b111111 #
1%
1$
1&
b10 ,
b100 +
#50000
b10 2
0%
0$
0&
b11 ,
b101 +
#55000
b10101101 :
b10101101 ?
b10101101 D
b10101101 G
b10101101 B
b10101101 F
b10101101 C
b10010101101 A
b10010101101 E
b10010101101 =
b10010101101 @
b10010101101 <
b111111 6
b111111 5
b111111 )
b111111 8
b10011 4
b10011 3
b10011 (
b10011 7
b0 !
b0 ;
b0 >
b11110 #
b1001 "
1%
1$
1&
b100 ,
b110 +
#60000
b11 2
0%
0$
0&
b101 ,
b111 +
#65000
b1110 :
b1110 ?
b1110 D
b1110 G
b1110 B
b1110 F
b100001110 C
b100001110 A
b100001110 E
b100001110 =
b100001110 @
b100001110 <
b1001 4
b1001 3
b1001 (
b1001 7
b11110 6
b11110 5
b11110 )
b11110 8
b10101101 !
b10101101 ;
b10101101 >
b101 "
b110010 #
1%
1$
1&
b110 ,
b1000 +
#70000
b100 2
0%
0$
0&
b111 ,
b1001 +
#75000
b11111010 :
b11111010 ?
b11111010 D
b11111010 G
b11111010 B
b11111010 F
b11111010 C
b11111010 A
b11111010 E
b11111010 =
b11111010 @
b11111010 <
b110010 6
b110010 5
b110010 )
b110010 8
b101 4
b101 3
b101 (
b101 7
b1110 !
b1110 ;
b1110 >
b110001 #
b1011 "
1%
1$
1&
b1000 ,
b1010 +
#80000
b101 2
0%
0$
0&
b1001 ,
b1011 +
#85000
b11011 :
b11011 ?
b11011 D
b11011 G
b11011 B
b11011 F
b11011 C
b1000011011 A
b1000011011 E
b1000011011 =
b1000011011 @
b1000011011 <
b1011 4
b1011 3
b1011 (
b1011 7
b110001 6
b110001 5
b110001 )
b110001 8
b11111010 !
b11111010 ;
b11111010 >
b10110 "
b10101 #
1%
1$
1&
b1010 ,
b1100 +
#90000
b110 2
0%
0$
0&
b1011 ,
b1101 +
#95000
b11001110 :
b11001110 ?
b11001110 D
b11001110 G
b11001110 B
b11001110 F
b111001110 C
b111001110 A
b111001110 E
b111001110 =
b111001110 @
b111001110 <
b10101 6
b10101 5
b10101 )
b10101 8
b10110 4
b10110 3
b10110 (
b10110 7
b11011 !
b11011 ;
b11011 >
1%
1$
1&
b1100 ,
b1110 +
#100000
b111 2
0%
0$
0&
b1101 ,
b1111 +
#105000
b11001110 !
b11001110 ;
b11001110 >
1%
1$
1&
b1110 ,
b10000 +
#110000
b1000 2
0%
0$
0&
b1111 ,
b10001 +
#115000
1%
1$
1&
b10000 ,
b10010 +
#120000
0%
0$
0&
b10001 ,
b10011 +
#125000
1%
1$
1&
b10010 ,
b10100 +
#130000
0%
0$
0&
b10011 ,
b10101 +
#135000
1%
1$
1&
b10100 ,
b10110 +
#140000
0%
0$
0&
b10101 ,
b10111 +
#145000
1%
1$
1&
b10110 ,
b11000 +
#150000
0%
0$
0&
b10111 ,
b11001 +
#155000
1%
1$
1&
b11000 ,
b11010 +
#160000
0%
0$
0&
b11001 ,
b11011 +
#165000
1%
1$
1&
b11010 ,
b11100 +
#170000
0%
0$
0&
b11011 ,
b11101 +
#175000
1%
1$
1&
b11100 ,
b11110 +
#180000
0%
0$
0&
b11101 ,
b11111 +
#185000
1%
1$
1&
b11110 ,
b100000 +
#190000
0%
0$
0&
b11111 ,
b100001 +
#195000
1%
1$
1&
b100000 ,
b100010 +
#200000
0%
0$
0&
b100001 ,
b100011 +
#205000
1%
1$
1&
b100010 ,
b100100 +
#210000
0%
0&
b100011 ,
#215000
1%
1&
b100100 ,
