Generator/Mul/V0.2.1/sim/config_case4/rtl/Delay0000000002.v
 module Delay0000000002 (
    i_data, o_data
    , i_clk
 );
 // Input and output ports
 input [8-1:0] i_data;
 output [8-1:0] o_data;
 input i_clk;
 reg [8-1:0] data_d [0:1-1];
 always @(posedge i_clk) begin
     data_d[0] <= i_data;
 end
 assign o_data = data_d[1-1];
 endmodule

Generator/Mul/V0.2.1/sim/config_case3/workspace/RTL/Delay0000000001.v
 module Delay0000000001 (
    i_data, o_data
 );
 // Input and output ports
 input [9-1:0] i_data;
 output [9-1:0] o_data;
 assign o_data = i_data;
 endmodule

Generator/Mul/V0.2.1/sim/config_case3/rtl/FxMatch0000000001.v
 module FxMatch0000000001 (
     i_data, o_data
 );
 input wire [10-1:0] i_data;     // Input data
 output wire [9-1:0] o_data;   // Output data
 //
 wire [11-1:0] i_data_eq;
 assign i_data_eq = {1'b0, i_data};
 wire [10-1:0] o_data_eq;
 // Quantization Stage
 // Pad extra LSB bits with 0
 wire [12-1:0] op_quan; // Quantization output
 assign op_quan = {i_data_eq, {1{1'b0}}};
 // Overflow Stage
 // Overflow protection
 assign o_data_eq = op_quan[10-1:0];
 wire [9-1:0] o_data_trunc;
 // Truncate the sign bit for unsigned output
 assign o_data_trunc = o_data_eq[10-2:0];
Delay0000000001  u_0000000001_Delay0000000001(.i_data(o_data_trunc), .o_data(o_data));
 endmodule

Generator/Mul/V0.2.1/sim/config_case3/workspace/RTL/Mul0000000001.v
 module Mul0000000001 (
 i_data_1, i_data_2, o_data
    ,i_clk
 );
 input wire [4:0] i_data_1;
 input wire [3:0] i_data_2;
 output wire [8:0] o_data;
 input wire i_clk;
 wire [4:0] data_1;
 wire [3:0] data_2;
 assign data_1 = i_data_1;
 assign data_2 = i_data_2;
 wire [4:0] data_1_abs;
 wire [3:0] data_2_abs;
 wire [8:0] data_mul_ures;
 assign data_1_abs =  data_1;
 assign data_2_abs =  data_2;
 assign data_mul_ures = data_1_abs * data_2_abs;
 wire res_sign;
 wire [9:0] data_mul_res;
 assign res_sign = 1'b0;
 assign data_mul_res = {1'b0, data_mul_ures};
 wire [8:0] result_fixed;
FxMatch0000000001  u_0000000001_FxMatch0000000001(.i_data(data_mul_res), .o_data(result_fixed));
Delay0000000002  u_0000000001_Delay0000000002(.i_data(result_fixed), .o_data(o_data), .i_clk(i_clk));
 endmodule

Generator/Mul/V0.2.1/sim/config_case3/workspace/RTL/TbMul0000000001.v
 `timescale 1ns/1ps
 module TbMul0000000001 ;
 // Inputs
 reg [5-1:0] Input_i_data_1;
 reg [4 -1:0] Input_i_data_2;
 reg [5-1:0] i_data_1;
 reg [4 -1:0] i_data_2;
 reg clk;
 reg en;
 reg i_rst_n;
 // Outputs
 wire [9-1:0] o_data;
 // Input ready and Output ready Indicators
 reg Input_rdy;
 reg Output_rdy;
 // Instantiate the DUT
 // Instantiate the DUT
Mul0000000001  u_0000000001_Mul0000000001(.i_data_1(i_data_1), .i_data_2(i_data_2), .o_data(o_data), .i_clk(clk));
 // Drive clk signal
 initial
 begin
     clk = 0;
      forever #2.5  clk <= ~clk;
 end
 // Initialize Inputs
 initial begin
 i_data_1 <= 'b0;
 i_data_2 <= 'b0;
 end
 // Enable signal
 initial begin
 en <= 0;
 repeat (3) @(posedge clk);
 en <= 1;
 end
 // Drive rst signal
 initial
 begin
     i_rst_n <= 1;
     repeat (1) @(negedge clk);
     i_rst_n <= 0;
     repeat (1) @(negedge clk);
     i_rst_n <= 1;
 end
 // Drive input ready and output ready signal
 integer Input_rdy_iter;
 initial begin
 Input_rdy <= 0;
 repeat (1) @(posedge en);
 Input_rdy <= 1;
 for (Input_rdy_iter=0; Input_rdy_iter<36; Input_rdy_iter=Input_rdy_iter+1) begin
     # (2.5) Input_rdy <= ~ Input_rdy;
 end
 end
 integer Output_rdy_iter;
 initial begin
 Output_rdy <= 0;
 repeat(1) @(posedge en);
 repeat (1) @(posedge clk); // wait for 1 cycles
 Output_rdy <= 1;
 for (Output_rdy_iter=0; Output_rdy_iter<36; Output_rdy_iter=Output_rdy_iter+1) begin
     # (2.5) Output_rdy <= ~ Output_rdy;
 end
 repeat(30) @(posedge clk);
 $finish;
 end
 // Drive input signal
 integer i_data_1_dat, i_data_1_st;
 initial begin
 repeat (2) @(posedge clk);
 i_data_1_dat = $fopen("../Input_Files/Mul_i_data_1.txt", "r");
 while (!$feof(i_data_1_dat)) begin
     i_data_1_st = $fscanf(i_data_1_dat, "%b\n", Input_i_data_1);
      repeat(1) @(posedge Input_rdy);
     i_data_1 <= Input_i_data_1;
 end
 $fclose(i_data_1_dat);
 end
 integer i_data_2_dat, i_data_2_st;
 initial begin
 repeat (2) @(posedge clk);
 i_data_2_dat = $fopen("../Input_Files/Mul_i_data_2.txt", "r");
 while (!$feof(i_data_2_dat)) begin
     i_data_2_st = $fscanf(i_data_2_dat, "%b\n", Input_i_data_2);
      repeat(1) @(posedge Input_rdy);
     i_data_2 <= Input_i_data_2;
 end
 $fclose(i_data_2_dat);
 end
 // Dump output signal
 integer o_data_dat;
 integer o_data_iter;
 initial begin
 repeat (2) @(posedge clk);
 o_data_dat = $fopen("../Output_Files/Mul_o_data.txt", "w");
 for (o_data_iter=0; o_data_iter<8; o_data_iter=o_data_iter+1) begin
     repeat(1) @(posedge Output_rdy);
     repeat(1) @(negedge clk);
     $fdisplay(o_data_dat, "%b", o_data);
 end
 $fclose(o_data_dat);
 end
 initial begin
     $dumpfile("wave.vcd");
     $dumpvars(0, TbMul0000000001);
 end
 endmodule

Generator/Mul/V0.2.1/sim/config_case3/wave.vcd
$date
	Fri Sep 11 10:48:55 2026
$end
$version
	Icarus Verilog
$end
$timescale
	1ps
$end
$scope module TbMul0000000001 $end
$var wire 9 ! o_data [8:0] $end
$var reg 5 " Input_i_data_1 [4:0] $end
$var reg 4 # Input_i_data_2 [3:0] $end
$var reg 1 $ Input_rdy $end
$var reg 1 % Output_rdy $end
$var reg 1 & clk $end
$var reg 1 ' en $end
$var reg 5 ( i_data_1 [4:0] $end
$var reg 4 ) i_data_2 [3:0] $end
$var reg 1 * i_rst_n $end
$var integer 32 + Input_rdy_iter [31:0] $end
$var integer 32 , Output_rdy_iter [31:0] $end
$var integer 32 - i_data_1_dat [31:0] $end
$var integer 32 . i_data_1_st [31:0] $end
$var integer 32 / i_data_2_dat [31:0] $end
$var integer 32 0 i_data_2_st [31:0] $end
$var integer 32 1 o_data_dat [31:0] $end
$var integer 32 2 o_data_iter [31:0] $end
$scope module u_0000000001_Mul0000000001 $end
$var wire 5 3 data_1 [4:0] $end
$var wire 5 4 data_1_abs [4:0] $end
$var wire 4 5 data_2 [3:0] $end
$var wire 4 6 data_2_abs [3:0] $end
$var wire 1 & i_clk $end
$var wire 5 7 i_data_1 [4:0] $end
$var wire 4 8 i_data_2 [3:0] $end
$var wire 1 9 res_sign $end
$var wire 9 : result_fixed [8:0] $end
$var wire 9 ; o_data [8:0] $end
$var wire 9 < data_mul_ures [8:0] $end
$var wire 10 = data_mul_res [9:0] $end
$scope module u_0000000001_Delay0000000002 $end
$var wire 1 & i_clk $end
$var wire 9 > o_data [8:0] $end
$var wire 9 ? i_data [8:0] $end
$upscope $end
$scope module u_0000000001_FxMatch0000000001 $end
$var wire 10 @ i_data [9:0] $end
$var wire 12 A op_quan [11:0] $end
$var wire 9 B o_data_trunc [8:0] $end
$var wire 10 C o_data_eq [9:0] $end
$var wire 9 D o_data [8:0] $end
$var wire 11 E i_data_eq [10:0] $end
$scope module u_0000000001_Delay0000000001 $end
$var wire 9 F i_data [8:0] $end
$var wire 9 G o_data [8:0] $end
$upscope $end
$upscope $end
$upscope $end
$upscope $end
$enddefinitions $end
$comment Show the parameter values. $end
$dumpall
$end
#0
$dumpvars
b0 G
b0 F
b0 E
b0 D
b0 C
b0 B
b0 A
b0 @
b0 ?
bx >
b0 =
b0 <
bx ;
b0 :
09
b0 8
b0 7
b0 6
b0 5
b0 4
b0 3
bx 2
bx 1
bx 0
bx /
bx .
bx -
bx ,
bx +
1*
b0 )
b0 (
0'
0&
0%
0$
bx #
bx "
bx !
$end
#2500
b0 !
b0 ;
b0 >
1&
#5000
0*
0&
#7500
b0 2
b10000000000000000000000000000101 1
b1 0
b1111 #
b10000000000000000000000000000100 /
b1 .
b11010 "
b10000000000000000000000000000011 -
1&
#10000
1*
0&
#12500
b100001100 :
b100001100 ?
b100001100 D
b100001100 G
b100001100 B
b100001100 F
b1100001100 C
b1100001100 A
b110000110 E
b110000110 =
b110000110 @
b110000110 <
b11010 4
b11010 3
b11010 (
b11010 7
b1111 6
b1111 5
b1111 )
b1111 8
b1110 "
b1101 #
1$
b0 +
1'
1&
#15000
0$
0&
b1 +
#17500
b101101100 :
b101101100 ?
b101101100 D
b101101100 G
b101101100 B
b101101100 F
b101101100 C
b101101100 A
b10110110 E
b10110110 =
b10110110 @
b10110110 <
b1101 6
b1101 5
b1101 )
b1101 8
b1110 4
b1110 3
b1110 (
b1110 7
b100001100 !
b100001100 ;
b100001100 >
1%
b100 #
b0 "
b0 ,
1$
1&
b10 +
#20000
b1 2
0%
0$
0&
b1 ,
b11 +
#22500
b0 :
b0 ?
b0 D
b0 G
b0 B
b0 F
b0 C
b0 A
b0 E
b0 =
b0 @
b0 <
b0 4
b0 3
b0 (
b0 7
b100 6
b100 5
b100 )
b100 8
b101101100 !
b101101100 ;
b101101100 >
b10011 "
b1111 #
1%
1$
1&
b10 ,
b100 +
#25000
b10 2
0%
0$
0&
b11 ,
b101 +
#27500
b111010 :
b111010 ?
b111010 D
b111010 G
b111010 B
b111010 F
b1000111010 C
b1000111010 A
b100011101 E
b100011101 =
b100011101 @
b100011101 <
b1111 6
b1111 5
b1111 )
b1111 8
b10011 4
b10011 3
b10011 (
b10011 7
b0 !
b0 ;
b0 >
b111 #
b1001 "
1%
1$
1&
b100 ,
b110 +
#30000
b11 2
0%
0$
0&
b101 ,
b111 +
#32500
b1111110 :
b1111110 ?
b1111110 D
b1111110 G
b1111110 B
b1111110 F
b1111110 C
b1111110 A
b111111 E
b111111 =
b111111 @
b111111 <
b1001 4
b1001 3
b1001 (
b1001 7
b111 6
b111 5
b111 )
b111 8
b111010 !
b111010 ;
b111010 >
b101 "
b1100 #
1%
1$
1&
b110 ,
b1000 +
#35000
b100 2
0%
0$
0&
b111 ,
b1001 +
#37500
b1111000 :
b1111000 ?
b1111000 D
b1111000 G
b1111000 B
b1111000 F
b1111000 C
b1111000 A
b111100 E
b111100 =
b111100 @
b111100 <
b1100 6
b1100 5
b1100 )
b1100 8
b101 4
b101 3
b101 (
b101 7
b1111110 !
b1111110 ;
b1111110 >
b1011 "
1%
1$
1&
b1000 ,
b1010 +
#40000
b101 2
0%
0$
0&
b1001 ,
b1011 +
#42500
b100001000 :
b100001000 ?
b100001000 D
b100001000 G
b100001000 B
b100001000 F
b100001000 C
b100001000 A
b10000100 E
b10000100 =
b10000100 @
b10000100 <
b1011 4
b1011 3
b1011 (
b1011 7
b1111000 !
b1111000 ;
b1111000 >
b10110 "
b101 #
1%
1$
1&
b1010 ,
b1100 +
#45000
b110 2
0%
0$
0&
b1011 ,
b1101 +
#47500
b11011100 :
b11011100 ?
b11011100 D
b11011100 G
b11011100 B
b11011100 F
b11011100 C
b11011100 A
b1101110 E
b1101110 =
b1101110 @
b1101110 <
b101 6
b101 5
b101 )
b101 8
b10110 4
b10110 3
b10110 (
b10110 7
b100001000 !
b100001000 ;
b100001000 >
1%
1$
1&
b1100 ,
b1110 +
#50000
b111 2
0%
0$
0&
b1101 ,
b1111 +
#52500
b11011100 !
b11011100 ;
b11011100 >
1%
1$
1&
b1110 ,
b10000 +
#55000
b1000 2
0%
0$
0&
b1111 ,
b10001 +
#57500
1%
1$
1&
b10000 ,
b10010 +
#60000
0%
0$
0&
b10001 ,
b10011 +
#62500
1%
1$
1&
b10010 ,
b10100 +
#65000
0%
0$
0&
b10011 ,
b10101 +
#67500
1%
1$
1&
b10100 ,
b10110 +
#70000
0%
0$
0&
b10101 ,
b10111 +
#72500
1%
1$
1&
b10110 ,
b11000 +
#75000
0%
0$
0&
b10111 ,
b11001 +
#77500
1%
1$
1&
b11000 ,
b11010 +
#80000
0%
0$
0&
b11001 ,
b11011 +
#82500
1%
1$
1&
b11010 ,
b11100 +
#85000
0%
0$
0&
b11011 ,
b11101 +
#87500
1%
1$
1&
b11100 ,
b11110 +
#90000
0%
0$
0&
b11101 ,
b11111 +
#92500
1%
1$
1&
b11110 ,
b100000 +
#95000
0%
0$
0&
b11111 ,
b100001 +
#97500
1%
1$
1&
b100000 ,
b100010 +
#100000
0%
0$
0&
b100001 ,
b100011 +
#102500
1%
1$
1&
b100010 ,
b100100 +
#105000
0%
0&
b100011 ,
#107500
1%
1&
b100100 ,
